spacenavigator.py
spacenavigator-0.2.3.dist-info/LICENSE
spacenavigator-0.2.3.dist-info/METADATA
spacenavigator-0.2.3.dist-info/WHEEL
spacenavigator-0.2.3.dist-info/top_level.txt
spacenavigator-0.2.3.dist-info/RECORD
